blackblox/__init__.py
blackblox/about.py
blackblox/bb_log.py
blackblox/calculators.py
blackblox/cli_app.py
blackblox/dataconfig.py
blackblox/dataconfig_defaults.py
blackblox/dataconfig_format.py
blackblox/factory.py
blackblox/frames_default.py
blackblox/industry.py
blackblox/io_functions.py
blackblox/parse_scenario.py
blackblox/processchain.py
blackblox/unitprocess.py
blackblox-0.3.dist-info/entry_points.txt
blackblox-0.3.dist-info/LICENSE
blackblox-0.3.dist-info/WHEEL
blackblox-0.3.dist-info/METADATA
blackblox-0.3.dist-info/RECORD
