Metadata-Version: 2.1
Name: blackblox
Version: 0.3
Summary: Simple simulator for black box process models
Home-page: https://concoctions.org/blackblox/
License: GPL-3.0-only
Author: S.E. Tanzer
Author-email: S.E.Tanzer@tudelft.nl
Requires-Python: >=3.8,<4.0
Classifier: License :: OSI Approved :: GNU General Public License v3 (GPLv3)
Classifier: Programming Language :: Python :: 3
Classifier: Programming Language :: Python :: 3.10
Classifier: Programming Language :: Python :: 3.8
Classifier: Programming Language :: Python :: 3.9
Requires-Dist: PyYAML (>=6.0,<7.0)
Requires-Dist: graphviz (>=0.16,<0.17)
Requires-Dist: matplotlib (>=3.4,<4.0)
Requires-Dist: molmass (>=2020.6.10,<2021.0.0)
Requires-Dist: numpy (>=1.20,<2.0)
Requires-Dist: openpyxl (>=3.0.7,<4.0.0)
Requires-Dist: pandas (==1.3.5)
Requires-Dist: xlrd (>=2.0.1,<3.0.0)
Project-URL: Repository, https://github.com/concoctions/BlackBlox
